dnp3_outstation/__init__.py
dnp3_outstation/agent.py
vdnp3_outstation/__init__.py
vdnp3_outstation/__main__.py
vdnp3_outstation/run_volttron_dnp3_outstation_cli.py
volttron_dnp3_outstation-2.0.0rc0.dist-info/LICENSE
volttron_dnp3_outstation-2.0.0rc0.dist-info/METADATA
volttron_dnp3_outstation-2.0.0rc0.dist-info/WHEEL
volttron_dnp3_outstation-2.0.0rc0.dist-info/entry_points.txt
volttron_dnp3_outstation-2.0.0rc0.dist-info/RECORD
