Metadata-Version: 2.1
Name: volttron-dnp3-outstation
Version: 2.0.0rc0
Summary: A Volttron agent that acts as a dnp3 outstation.
Home-page: https://github.com/eclipse-volttron/volttron-dnp3-outstation
License: Apache-2.0
Keywords: volttron,agent,dnp3,outstation,application
Author: Kefei Mo
Author-email: kefei.mo@pnnl.gov
Maintainer: Volttron Team
Maintainer-email: volttron@pnnl.gov
Requires-Python: >=3.10,<4.0
Classifier: Development Status :: 3 - Alpha
Classifier: Intended Audience :: Developers
Classifier: Intended Audience :: Science/Research
Classifier: License :: OSI Approved :: Apache Software License
Classifier: Programming Language :: Python :: 3
Classifier: Programming Language :: Python :: 3.10
Classifier: Programming Language :: Python :: 3.11
Classifier: Programming Language :: Python :: 3.12
Classifier: Topic :: Home Automation
Classifier: Topic :: Software Development :: Embedded Systems
Requires-Dist: dnp3-python (>=0.2.3b3,<0.3.0)
Requires-Dist: volttron-core (>=2.0.0rc0)
Project-URL: Bug Tracker, https://github.com/eclipse-volttron/volttron-dnp3-outstation/issues
Project-URL: Repository, https://github.com/eclipse-volttron/volttron-dnp3-outstation
